fazlamesai.py
setup.py
fazlamesai.egg-info/PKG-INFO
fazlamesai.egg-info/SOURCES.txt
fazlamesai.egg-info/dependency_links.txt
fazlamesai.egg-info/requires.txt
fazlamesai.egg-info/top_level.txt