Metadata-Version: 1.0
Name: fazlamesai
Version: 0.1.0
Summary: A client library for the fazlamesai.net API
Home-page: https://github.com/gkbrk/fazlamesai-py
Author: Gokberk Yaltirakli
Author-email: webdosusb@gmail.com
License: UNKNOWN
Keywords: fazlamesai,api,client
Platform: UNKNOWN
